{"url":"https://molns-organization.gitbook.io/untitled","domain":"molns-organization.gitbook.io","lastScraped":"2025-10-23T12:47:19.248Z","totalPages":5,"successfulPages":5,"failedPages":[],"structure":[{"type":"Page | Untitled","url":"https://molns-organization.gitbook.io/untitled"},{"type":"Support | Untitled","url":"https://molns-organization.gitbook.io/untitled/group-1/support"},{"type":"How are you | Untitled","url":"https://molns-organization.gitbook.io/untitled/how-are-you"},{"type":"Page 1 | Untitled","url":"https://molns-organization.gitbook.io/untitled/group-1/page-1"},{"type":"Page 1 | Untitled","url":"https://molns-organization.gitbook.io/untitled/group-1"}]}
