{"url":"https://docs.polymarket.com/changelog/changelog","domain":"docs.polymarket.com","lastScraped":"2025-08-31T17:48:50.243Z","totalPages":84,"successfulPages":84,"failedPages":[],"structure":[{"type":"Polymarket Changelog - Polymarket Documentation","url":"https://docs.polymarket.com/changelog/changelog"},{"type":"Get comments by comment id - Polymarket Documentation","url":"https://docs.polymarket.com/api-reference/comments/get-comments-by-comment-id"},{"type":"Endpoints - Polymarket Documentation","url":"https://docs.polymarket.com/developers/CLOB/endpoints"},{"type":"Get bid-ask spreads - Polymarket Documentation","url":"https://docs.polymarket.com/api-reference/spreads/get-bid-ask-spreads"},{"type":"List teams - Polymarket Documentation","url":"https://docs.polymarket.com/api-reference/sports/list-teams"},{"type":"Clients - Polymarket Documentation","url":"https://docs.polymarket.com/developers/CLOB/clients"},{"type":"Status - Polymarket Documentation","url":"https://docs.polymarket.com/developers/CLOB/status"},{"type":"CLOB Introduction - Polymarket Documentation","url":"https://docs.polymarket.com/developers/CLOB/introduction"},{"type":"Check Order Reward Scoring - Polymarket Documentation","url":"https://docs.polymarket.com/developers/CLOB/orders/check-scoring"},{"type":"Onchain Order Info - Polymarket Documentation","url":"https://docs.polymarket.com/developers/CLOB/orders/onchain-order-info"},{"type":"Get Active Orders - Polymarket Documentation","url":"https://docs.polymarket.com/developers/CLOB/orders/get-active-order"},{"type":"How Do I Export My Key? - Polymarket Documentation","url":"https://docs.polymarket.com/polymarket-learn/FAQ/how-to-export-private-key"},{"type":"Can I Sell Early? - Polymarket Documentation","url":"https://docs.polymarket.com/polymarket-learn/FAQ/sell-early"},{"type":"Does Polymarket Have a Token? - Polymarket Documentation","url":"https://docs.polymarket.com/polymarket-learn/FAQ/wen-token"},{"type":"How Do I Contact Support? - Polymarket Documentation","url":"https://docs.polymarket.com/polymarket-learn/FAQ/support"},{"type":"Deposit with Coinbase - Polymarket Documentation","url":"https://docs.polymarket.com/polymarket-learn/deposits/coinbase"},{"type":"Get Order - Polymarket Documentation","url":"https://docs.polymarket.com/developers/CLOB/orders/get-order"},{"type":"Polymarket vs. Polling - Polymarket Documentation","url":"https://docs.polymarket.com/polymarket-learn/FAQ/polling"},{"type":"Why Crypto? - Polymarket Documentation","url":"https://docs.polymarket.com/polymarket-learn/FAQ/why-do-i-need-crypto"},{"type":"How to Withdraw - Polymarket Documentation","url":"https://docs.polymarket.com/polymarket-learn/deposits/how-to-withdraw"},{"type":"Large Cross Chain Deposits - Polymarket Documentation","url":"https://docs.polymarket.com/polymarket-learn/deposits/large-cross-chain-deposits"},{"type":"How To Use Embeds - Polymarket Documentation","url":"https://docs.polymarket.com/polymarket-learn/FAQ/embeds"},{"type":"Does Polymarket have an API? - Polymarket Documentation","url":"https://docs.polymarket.com/polymarket-learn/FAQ/does-polymarket-have-an-api"},{"type":"Trades Overview - Polymarket Documentation","url":"https://docs.polymarket.com/developers/CLOB/trades/trades-overview"},{"type":"Trading Fees - Polymarket Documentation","url":"https://docs.polymarket.com/polymarket-learn/trading/fees"},{"type":"Is Polymarket The House? - Polymarket Documentation","url":"https://docs.polymarket.com/polymarket-learn/FAQ/is-polymarket-the-house"},{"type":"Recover Missing Deposit - Polymarket Documentation","url":"https://docs.polymarket.com/polymarket-learn/FAQ/recover-missing-deposit"},{"type":"What is a Prediction Market? - Polymarket Documentation","url":"https://docs.polymarket.com/polymarket-learn/FAQ/what-are-prediction-markets"},{"type":"Deposit USDC on Ethereum - Polymarket Documentation","url":"https://docs.polymarket.com/polymarket-learn/deposits/usdc-on-eth"},{"type":"How Are Markets Created? - Polymarket Documentation","url":"https://docs.polymarket.com/polymarket-learn/markets/how-are-markets-created"},{"type":"Cancel Orders(s) - Polymarket Documentation","url":"https://docs.polymarket.com/developers/CLOB/orders/cancel-orders"},{"type":"WSS Authentication - Polymarket Documentation","url":"https://docs.polymarket.com/developers/CLOB/websocket/wss-auth"},{"type":"Deposit Using Your Card - Polymarket Documentation","url":"https://docs.polymarket.com/polymarket-learn/deposits/moonpay"},{"type":"How to Sign-Up - Polymarket Documentation","url":"https://docs.polymarket.com/polymarket-learn/get-started/how-to-signup"},{"type":"How Are Markets Disputed? - Polymarket Documentation","url":"https://docs.polymarket.com/polymarket-learn/markets/dispute"},{"type":"Orders Overview - Polymarket Documentation","url":"https://docs.polymarket.com/developers/CLOB/orders/orders"},{"type":"WSS Overview - Polymarket Documentation","url":"https://docs.polymarket.com/developers/CLOB/websocket/wss-overview"},{"type":"Reedeeming Tokens - Polymarket Documentation","url":"https://docs.polymarket.com/developers/CTF/redeem"},{"type":"Merging Tokens - Polymarket Documentation","url":"https://docs.polymarket.com/developers/CTF/merge"},{"type":"Deployment and Additional Information - Polymarket Documentation","url":"https://docs.polymarket.com/developers/CTF/deployment-resources"},{"type":"Overview - Polymarket Documentation","url":"https://docs.polymarket.com/developers/gamma-markets-api/overview"},{"type":"Is My Money Safe? - Polymarket Documentation","url":"https://docs.polymarket.com/polymarket-learn/FAQ/is-my-money-safe"},{"type":"Authentication - Polymarket Documentation","url":"https://docs.polymarket.com/developers/CLOB/authentication"},{"type":"Splitting USDC - Polymarket Documentation","url":"https://docs.polymarket.com/developers/CTF/split"},{"type":"Overview - Polymarket Documentation","url":"https://docs.polymarket.com/developers/CTF/overview"},{"type":"Get Trades - Polymarket Documentation","url":"https://docs.polymarket.com/developers/CLOB/trades/trades"},{"type":"How Are Prediction Markets Resolved? - Polymarket Documentation","url":"https://docs.polymarket.com/polymarket-learn/markets/how-are-markets-resolved"},{"type":"How Are Markets Clarified? - Polymarket Documentation","url":"https://docs.polymarket.com/polymarket-learn/markets/how-are-markets-clarified"},{"type":"Does Polymarket Have Trading Limits? - Polymarket Documentation","url":"https://docs.polymarket.com/polymarket-learn/trading/no-limits"},{"type":"Overview - Polymarket Documentation","url":"https://docs.polymarket.com/developers/neg-risk/overview"},{"type":"Deposit by Transfering Crypto - Polymarket Documentation","url":"https://docs.polymarket.com/polymarket-learn/deposits/supported-tokens"},{"type":"How Are Prices Calculated? - Polymarket Documentation","url":"https://docs.polymarket.com/polymarket-learn/trading/how-are-prices-calculated"},{"type":"Limit Orders - Polymarket Documentation","url":"https://docs.polymarket.com/polymarket-learn/trading/limit-orders"},{"type":"Gamma Structure - Polymarket Documentation","url":"https://docs.polymarket.com/developers/gamma-markets-api/gamma-structure"},{"type":"Proxy wallet - Polymarket Documentation","url":"https://docs.polymarket.com/developers/proxy-wallet"},{"type":"Making Your First Trade - Polymarket Documentation","url":"https://docs.polymarket.com/polymarket-learn/get-started/making-your-first-trade"},{"type":"Resolution - Polymarket Documentation","url":"https://docs.polymarket.com/developers/resolution/UMA"},{"type":"Market Orders - Polymarket Documentation","url":"https://docs.polymarket.com/polymarket-learn/trading/market-orders"},{"type":"Holding Rewards - Polymarket Documentation","url":"https://docs.polymarket.com/polymarket-learn/trading/holding-rewards"},{"type":"Get tag by id - Polymarket Documentation","url":"https://docs.polymarket.com/api-reference/tags/get-tag-by-id"},{"type":"Get related tags (relationships) by tag slug - Polymarket Documentation","url":"https://docs.polymarket.com/api-reference/tags/get-related-tags-relationships-by-tag-slug"},{"type":"Get related tags (relationships) by tag id - Polymarket Documentation","url":"https://docs.polymarket.com/api-reference/tags/get-related-tags-relationships-by-tag-id"},{"type":"Overview - Polymarket Documentation","url":"https://docs.polymarket.com/developers/subgraph/overview"},{"type":"Liquidity Rewards - Polymarket Documentation","url":"https://docs.polymarket.com/polymarket-learn/trading/liquidity-rewards"},{"type":"Get tag by slug - Polymarket Documentation","url":"https://docs.polymarket.com/api-reference/tags/get-tag-by-slug"},{"type":"How to Deposit - Polymarket Documentation","url":"https://docs.polymarket.com/polymarket-learn/get-started/how-to-deposit"},{"type":"Market Channel - Polymarket Documentation","url":"https://docs.polymarket.com/developers/CLOB/websocket/market-channel"},{"type":"User Channel - Polymarket Documentation","url":"https://docs.polymarket.com/developers/CLOB/websocket/user-channel"},{"type":"API Rate Limits - Polymarket Documentation","url":"https://docs.polymarket.com/quickstart/introduction/rate-limits"},{"type":"Place Single Order - Polymarket Documentation","url":"https://docs.polymarket.com/developers/CLOB/orders/create-order"},{"type":"Get tags related to a tag id - Polymarket Documentation","url":"https://docs.polymarket.com/api-reference/tags/get-tags-related-to-a-tag-id"},{"type":"Using the Order Book - Polymarket Documentation","url":"https://docs.polymarket.com/polymarket-learn/trading/using-the-orderbook"},{"type":"Place Multiple Orders (Batching) - Polymarket Documentation","url":"https://docs.polymarket.com/developers/CLOB/orders/create-order-batch"},{"type":"Get tags related to a tag slug - Polymarket Documentation","url":"https://docs.polymarket.com/api-reference/tags/get-tags-related-to-a-tag-slug"},{"type":"List tags - Polymarket Documentation","url":"https://docs.polymarket.com/api-reference/tags/list-tags"},{"type":"What is Polymarket? - Polymarket Documentation","url":"https://docs.polymarket.com/polymarket-learn/get-started/what-is-polymarket"},{"type":"Developer Quickstart - Polymarket Documentation","url":"https://docs.polymarket.com/quickstart/introduction/main"},{"type":"Glossary - Polymarket Documentation","url":"https://docs.polymarket.com/quickstart/introduction/definitions"},{"type":"WSS Quickstart - Polymarket Documentation","url":"https://docs.polymarket.com/quickstart/websocket/WSS-Quickstart"},{"type":"Your First Order - Polymarket Documentation","url":"https://docs.polymarket.com/quickstart/orders/first-order"},{"type":"Liquidity Rewards - Polymarket Documentation","url":"https://docs.polymarket.com/developers/rewards/overview"},{"type":"API Showcase - Polymarket Documentation","url":"https://docs.polymarket.com/quickstart/introduction/showcase"},{"type":"Get Events - Polymarket Documentation","url":"https://docs.polymarket.com/developers/gamma-markets-api/get-events"},{"type":"Get Markets - Polymarket Documentation","url":"https://docs.polymarket.com/developers/gamma-markets-api/get-markets"}]}
