{"url":"https://web3whales.gitbook.io/whitepaper","domain":"web3whales.gitbook.io","lastScraped":"2025-07-16T09:55:00.250Z","totalPages":3,"successfulPages":3,"failedPages":[],"structure":[{"type":"Introduction | Web3Whales","url":"https://web3whales.gitbook.io/whitepaper"},{"type":"Vesting & Distribution | Web3Whales","url":"https://web3whales.gitbook.io/whitepaper/tokenomics/vesting-and-distribution"},{"type":"Private Sale A | Web3Whales","url":"https://web3whales.gitbook.io/whitepaper/tokenomics/vesting-and-distribution/private-sale-a"}]}
