{"url":"https://owl-bot.gitbook.io/docs","domain":"owl-bot.gitbook.io","lastScraped":"2025-08-31T01:30:23.396Z","totalPages":24,"successfulPages":24,"failedPages":[],"structure":[{"type":"Welcome to OWL | OWL","url":"https://owl-bot.gitbook.io/docs"},{"type":"High MC Large Buys | OWL","url":"https://owl-bot.gitbook.io/docs/alert-channels/high-mc-large-buys"},{"type":"What OWL Does | OWL","url":"https://owl-bot.gitbook.io/docs/introduction/what-owl-does"},{"type":"Low MC Small Buys | OWL","url":"https://owl-bot.gitbook.io/docs/alert-channels/low-mc-small-buys"},{"type":"How It Works | OWL","url":"https://owl-bot.gitbook.io/docs/introduction/how-it-works"},{"type":"Unknown","url":"https://owl-bot.gitbook.io/docs/alert-channels/dormant-wallet-awakening"},{"type":"Low MC Large Buys | OWL","url":"https://owl-bot.gitbook.io/docs/alert-channels/low-mc-large-buys"},{"type":"High MC Small Buys | OWL","url":"https://owl-bot.gitbook.io/docs/alert-channels/high-mc-small-buys"},{"type":"Developer Buy Detection | OWL","url":"https://owl-bot.gitbook.io/docs/decoding-alerts/developer-buy-detection"},{"type":"Freshie Metrics Breakdown | OWL","url":"https://owl-bot.gitbook.io/docs/decoding-alerts/freshie-metrics-breakdown"},{"type":"Jupiter DCA Alerts | OWL","url":"https://owl-bot.gitbook.io/docs/alert-channels/jupiter-dca-alerts"},{"type":"Detailed AI Image Detection | OWL","url":"https://owl-bot.gitbook.io/docs/decoding-alerts/detailed-ai-image-detection"},{"type":"High Fresh Surge | OWL","url":"https://owl-bot.gitbook.io/docs/alert-channels/high-fresh-surge"},{"type":"Wallet Hyperlinks | OWL","url":"https://owl-bot.gitbook.io/docs/transaction-details/wallet-hyperlinks"},{"type":"Chain alerts | OWL","url":"https://owl-bot.gitbook.io/docs/alert-channels/chain-alerts"},{"type":"Post bond alerts | OWL","url":"https://owl-bot.gitbook.io/docs/alert-channels/post-bond-alerts"},{"type":"Prebond Alerts | OWL","url":"https://owl-bot.gitbook.io/docs/alert-channels/prebond-alerts"},{"type":"Swap Alert Breakdown | OWL","url":"https://owl-bot.gitbook.io/docs/decoding-alerts/swap-alert-breakdown"},{"type":"Decoding Swap Transactions | OWL","url":"https://owl-bot.gitbook.io/docs/decoding-alerts/decoding-swap-transactions"},{"type":"Fees & Tips | OWL","url":"https://owl-bot.gitbook.io/docs/transaction-details/fees-and-tips"},{"type":"Low MC Small Buys | OWL","url":"https://owl-bot.gitbook.io/docs/alert-channels"},{"type":"How It Works | OWL","url":"https://owl-bot.gitbook.io/docs/introduction"},{"type":"Swap Alert Breakdown | OWL","url":"https://owl-bot.gitbook.io/docs/decoding-alerts"},{"type":"Fees & Tips | OWL","url":"https://owl-bot.gitbook.io/docs/transaction-details"}]}
