{
  "url": "https://docs.shipbubble.com",
  "domain": "docs.shipbubble.com",
  "lastScraped": "2026-03-21T23:43:43.979Z",
  "totalPages": 51,
  "successfulPages": 51,
  "failedPages": [],
  "structure": [
    {
      "type": "Shipbubble API | Shipbubble API Documentation",
      "url": "https://docs.shipbubble.com"
    },
    {
      "type": "Get started | Shipbubble API Documentation",
      "url": "https://docs.shipbubble.com/get-started"
    },
    {
      "type": "Authentication | Shipbubble API Documentation",
      "url": "https://docs.shipbubble.com/get-started/authentication"
    },
    {
      "type": "Errors | Shipbubble API Documentation",
      "url": "https://docs.shipbubble.com/get-started/errors"
    },
    {
      "type": "Rate Limiting | Shipbubble API Documentation",
      "url": "https://docs.shipbubble.com/get-started/rate-limiting"
    },
    {
      "type": "Request and Responses | Shipbubble API Documentation",
      "url": "https://docs.shipbubble.com/get-started/request-and-responses"
    },
    {
      "type": "Pagination | Shipbubble API Documentation",
      "url": "https://docs.shipbubble.com/get-started/pagination"
    },
    {
      "type": "Postman | Shipbubble API Documentation",
      "url": "https://docs.shipbubble.com/get-started/postman"
    },
    {
      "type": "Get shipping wallet balance | Shipbubble API Documentation",
      "url": "https://docs.shipbubble.com/api-reference/wallet/get-shipping-wallet-balance"
    },
    {
      "type": "Request wallet fund | Shipbubble API Documentation",
      "url": "https://docs.shipbubble.com/api-reference/wallet/request-wallet-fund"
    },
    {
      "type": "Validate address (global) | Shipbubble API Documentation",
      "url": "https://docs.shipbubble.com/api-reference/addresses/validate-address-global"
    },
    {
      "type": "Addresses | Shipbubble API Documentation",
      "url": "https://docs.shipbubble.com/api-reference/addresses"
    },
    {
      "type": "Get validated addresses | Shipbubble API Documentation",
      "url": "https://docs.shipbubble.com/api-reference/addresses/get-validated-addresses"
    },
    {
      "type": "Wallet | Shipbubble API Documentation",
      "url": "https://docs.shipbubble.com/api-reference/wallet"
    },
    {
      "type": "Package categories | Shipbubble API Documentation",
      "url": "https://docs.shipbubble.com/api-reference/package-categories"
    },
    {
      "type": "Rates | Shipbubble API Documentation",
      "url": "https://docs.shipbubble.com/api-reference/rates"
    },
    {
      "type": "Package dimensions | Shipbubble API Documentation",
      "url": "https://docs.shipbubble.com/api-reference/package-dimensions"
    },
    {
      "type": "View courier coverage areas | Shipbubble API Documentation",
      "url": "https://docs.shipbubble.com/api-reference/couriers/view-courier-coverage-areas"
    },
    {
      "type": "Get single address details | Shipbubble API Documentation",
      "url": "https://docs.shipbubble.com/api-reference/addresses/get-single-address-details"
    },
    {
      "type": "View courier integrations | Shipbubble API Documentation",
      "url": "https://docs.shipbubble.com/api-reference/couriers/view-courier-integrations"
    },
    {
      "type": "Couriers | Shipbubble API Documentation",
      "url": "https://docs.shipbubble.com/api-reference/couriers"
    },
    {
      "type": "Cash on delivery | Shipbubble API Documentation",
      "url": "https://docs.shipbubble.com/api-reference/cash-on-delivery"
    },
    {
      "type": "Edit address details | Shipbubble API Documentation",
      "url": "https://docs.shipbubble.com/api-reference/addresses/edit-address-details"
    },
    {
      "type": "Insurance | Shipbubble API Documentation",
      "url": "https://docs.shipbubble.com/api-reference/insurance"
    },
    {
      "type": "Returns | Shipbubble API Documentation",
      "url": "https://docs.shipbubble.com/api-reference/returns"
    },
    {
      "type": "Cancel shipment | Shipbubble API Documentation",
      "url": "https://docs.shipbubble.com/api-reference/shipments/cancel-shipment"
    },
    {
      "type": "Shipments | Shipbubble API Documentation",
      "url": "https://docs.shipbubble.com/api-reference/shipments"
    },
    {
      "type": "Tracking | Shipbubble API Documentation",
      "url": "https://docs.shipbubble.com/api-reference/tracking"
    },
    {
      "type": "Request shipping rates | Shipbubble API Documentation",
      "url": "https://docs.shipbubble.com/api-reference/rates/request-shipping-rates"
    },
    {
      "type": "Request shipping rates from selected couriers | Shipbubble API Documentation",
      "url": "https://docs.shipbubble.com/api-reference/rates/request-shipping-rates-from-selected-couriers"
    },
    {
      "type": "Get rates for a return shipment request | Shipbubble API Documentation",
      "url": "https://docs.shipbubble.com/api-reference/returns/get-rates-for-a-return-shipment-request"
    },
    {
      "type": "Webhooks | Shipbubble API Documentation",
      "url": "https://docs.shipbubble.com/api-reference/webhooks"
    },
    {
      "type": "Stores | Shipbubble API Documentation",
      "url": "https://docs.shipbubble.com/api-reference/marketplaces/stores"
    },
    {
      "type": "Webhook simulator (sandbox) | Shipbubble API Documentation",
      "url": "https://docs.shipbubble.com/api-reference/webhooks/webhook-simulator-sandbox"
    },
    {
      "type": "Marketplaces | Shipbubble API Documentation",
      "url": "https://docs.shipbubble.com/api-reference/marketplaces"
    },
    {
      "type": "Create shipment | Shipbubble API Documentation",
      "url": "https://docs.shipbubble.com/api-reference/shipments/create-shipment"
    },
    {
      "type": "Get multiple specific shipments | Shipbubble API Documentation",
      "url": "https://docs.shipbubble.com/api-reference/tracking/get-multiple-specific-shipments"
    },
    {
      "type": "Products | Shipbubble API Documentation",
      "url": "https://docs.shipbubble.com/api-reference/marketplaces/products"
    },
    {
      "type": "Delete store products | Shipbubble API Documentation",
      "url": "https://docs.shipbubble.com/api-reference/marketplaces/products/delete-store-products"
    },
    {
      "type": "Create single product | Shipbubble API Documentation",
      "url": "https://docs.shipbubble.com/api-reference/marketplaces/products/create-single-product"
    },
    {
      "type": "Get shipments | Shipbubble API Documentation",
      "url": "https://docs.shipbubble.com/api-reference/tracking/get-shipments"
    },
    {
      "type": "Edit request token details | Shipbubble API Documentation",
      "url": "https://docs.shipbubble.com/api-reference/rates/edit-request-token-details"
    },
    {
      "type": "Get store products | Shipbubble API Documentation",
      "url": "https://docs.shipbubble.com/api-reference/marketplaces/products/get-store-products"
    },
    {
      "type": "Delete store | Shipbubble API Documentation",
      "url": "https://docs.shipbubble.com/api-reference/marketplaces/stores/delete-store"
    },
    {
      "type": "Get stores | Shipbubble API Documentation",
      "url": "https://docs.shipbubble.com/api-reference/marketplaces/stores/get-stores"
    },
    {
      "type": "Create variable product | Shipbubble API Documentation",
      "url": "https://docs.shipbubble.com/api-reference/marketplaces/products/create-variable-product"
    },
    {
      "type": "Update store product | Shipbubble API Documentation",
      "url": "https://docs.shipbubble.com/api-reference/marketplaces/products/update-store-product"
    },
    {
      "type": "Create store | Shipbubble API Documentation",
      "url": "https://docs.shipbubble.com/api-reference/marketplaces/stores/create-store"
    },
    {
      "type": "Get Insurance Rates | Shipbubble API Documentation",
      "url": "https://docs.shipbubble.com/api-reference/insurance/get-insurance-rates"
    },
    {
      "type": "Wallet | Shipbubble API Documentation",
      "url": "https://docs.shipbubble.com/api-reference"
    },
    {
      "type": "Email Protection | Cloudflare",
      "url": "https://docs.shipbubble.com/cdn-cgi/l/email-protection"
    }
  ],
  "latestVersion": "1.0.0",
  "versions": [
    {
      "version": "1.0.0",
      "label": "latest",
      "timestamp": "2026-03-21T23:43:43.979Z",
      "filename": "documentation_2026-03-21T23:43:43.979Z.md",
      "totalPages": 51,
      "successfulPages": 51,
      "url": "https://docs.shipbubble.com",
      "isLatest": true
    }
  ],
  "schemaVersion": 2
}
